{
  "version": "1.0.0",
  "restore": {
    "projectUniqueName": "/Users/helicoptera/Desktop/MPP/Faker/Faker/Faker.csproj",
    "projectName": "Faker",
    "projectPath": "/Users/helicoptera/Desktop/MPP/Faker/Faker/Faker.csproj",
    "outputPath": "/Users/helicoptera/Desktop/MPP/Faker/Faker/obj/",
    "projectStyle": "PackageReference",
    "originalTargetFrameworks": [
      "netcoreapp3.1"
    ],
    "sources": {
      "https://api.nuget.org/v3/index.json": {}
    },
    "frameworks": {
      "netcoreapp3.1": {
        "projectReferences": {
          "/Users/helicoptera/Desktop/MPP/Faker/PluginBase/PluginBase.csproj": {
            "projectPath": "/Users/helicoptera/Desktop/MPP/Faker/PluginBase/PluginBase.csproj"
          }
        }
      }
    },
    "warningProperties": {
      "warnAsError": [
        "NU1605"
      ]
    }
  },
  "frameworks": {
    "netcoreapp3.1": {
      "imports": [
        "net461",
        "net462",
        "net47",
        "net471",
        "net472",
        "net48"
      ],
      "assetTargetFallback": true,
      "warn": true,
      "frameworkReferences": {
        "Microsoft.NETCore.App": {
          "privateAssets": "all"
        }
      },
      "runtimeIdentifierGraphPath": "/Users/helicoptera/.dotnet/sdk/3.1.302/RuntimeIdentifierGraph.json"
    }
  }
}